DDCO/3/dataflowmodel.v
// Dataflow Modeling
module dataflow(A, B, C, D, E);
    input A, B, C, D;
    output E;
    assign E = A | (B & C) | (~B & D);
endmodule

module dataflow_tb();
    reg A, B, C, D;
    wire E;

    dataflow EX(.A(A), .B(B), .C(C), .D(D), .E(E));

    initial begin
        $dumpfile("data.vcd");
        $dumpvars(0, dataflow_tb);
        A=0; B=0; C=0; D=0; #10;
        A=0; B=0; C=0; D=1; #10;
        A=0; B=0; C=1; D=0; #10;
        A=0; B=0; C=1; D=1; #10;
        A=0; B=1; C=0; D=0; #10;
        A=0; B=1; C=0; D=1; #10;
        A=0; B=1; C=1; D=0; #10;
        A=0; B=1; C=1; D=1; #10;
        A=1; B=0; C=0; D=0; #10;
        A=1; B=0; C=0; D=1; #10;
        A=1; B=0; C=1; D=0; #10;
        A=1; B=0; C=1; D=1; #10;
        A=1; B=1; C=0; D=0; #10;
        A=1; B=1; C=0; D=1; #10;
        A=1; B=1; C=1; D=0; #10;
        A=1; B=1; C=1; D=1; #10;
    end
endmodule

DDCO/3/data.vcd
$date
	Sat Oct 18 01:48:14 2025
$end
$version
	Icarus Verilog
$end
$timescale
	1s
$end
$scope module dataflow_tb $end
$var wire 1 ! E $end
$var reg 1 " A $end
$var reg 1 # B $end
$var reg 1 $ C $end
$var reg 1 % D $end
$scope module EX $end
$var wire 1 " A $end
$var wire 1 # B $end
$var wire 1 $ C $end
$var wire 1 % D $end
$var wire 1 ! E $end
$upscope $end
$upscope $end
$enddefinitions $end
#0
$dumpvars
0%
0$
0#
0"
0!
$end
#10
1!
1%
#20
0!
0%
1$
#30
1!
1%
#40
0!
0%
0$
1#
#50
1%
#60
1!
0%
1$
#70
1%
#80
0%
0$
0#
1"
#90
1%
#100
0%
1$
#110
1%
#120
0%
0$
1#
#130
1%
#140
0%
1$
#150
1%
