DDCO/7/de_mul_8_1.v
// 8:1 Demultiplexer
module Demux8to1(I, S0, S1, S2, Y0, Y1, Y2, Y3, Y4, Y5, Y6, Y7);
    input I, S0, S1, S2;
    output Y0, Y1, Y2, Y3, Y4, Y5, Y6, Y7;

    assign Y0 = (~S0) & (~S1) & (~S2) & I;
    assign Y1 = (~S0) & (~S1) & ( S2) & I;
    assign Y2 = (~S0) & ( S1) & (~S2) & I;
    assign Y3 = (~S0) & ( S1) & ( S2) & I;
    assign Y4 = ( S0) & (~S1) & (~S2) & I;
    assign Y5 = ( S0) & (~S1) & ( S2) & I;
    assign Y6 = ( S0) & ( S1) & (~S2) & I;
    assign Y7 = ( S0) & ( S1) & ( S2) & I;

endmodule


module Demux8to1_TB();
    reg I, S0, S1, S2;
    wire Y0, Y1, Y2, Y3, Y4, Y5, Y6, Y7;

    Demux8to1 DEMUX(
        I, S0, S1, S2,
        Y0, Y1, Y2, Y3, Y4, Y5, Y6, Y7
    );

    initial begin
        $dumpfile("demux8.vcd");
        $dumpvars(0, Demux8to1_TB);

        $monitor(
          "Time=%0t  S2=%b S1=%b S0=%b  I=%b  |  Y0=%b Y1=%b Y2=%b Y3=%b Y4=%b Y5=%b Y6=%b Y7=%b",
          $time, S2, S1, S0, I,
          Y0, Y1, Y2, Y3, Y4, Y5, Y6, Y7
        );

        S0=0; S1=0; S2=0; I=1; #10;
        S0=0; S1=0; S2=1; I=1; #10;
        S0=0; S1=1; S2=0; I=1; #10;
        S0=0; S1=1; S2=1; I=1; #10;
        S0=1; S1=0; S2=0; I=1; #10;
        S0=1; S1=0; S2=1; I=1; #10;
        S0=1; S1=1; S2=0; I=1; #10;
        S0=1; S1=1; S2=1; I=1; #10;

        $finish;
    end
endmodule

3rd Sem/DDCO/7/demux8.vcd
$date
	Tue Dec 16 11:40:41 2025
$end
$version
	Icarus Verilog
$end
$timescale
	1s
$end
$scope module Demux8to1_TB $end
$var wire 1 ! Y7 $end
$var wire 1 " Y6 $end
$var wire 1 # Y5 $end
$var wire 1 $ Y4 $end
$var wire 1 % Y3 $end
$var wire 1 & Y2 $end
$var wire 1 ' Y1 $end
$var wire 1 ( Y0 $end
$var reg 1 ) I $end
$var reg 1 * S0 $end
$var reg 1 + S1 $end
$var reg 1 , S2 $end
$scope module DEMUX $end
$var wire 1 ) I $end
$var wire 1 * S0 $end
$var wire 1 + S1 $end
$var wire 1 , S2 $end
$var wire 1 ( Y0 $end
$var wire 1 ' Y1 $end
$var wire 1 & Y2 $end
$var wire 1 % Y3 $end
$var wire 1 $ Y4 $end
$var wire 1 # Y5 $end
$var wire 1 " Y6 $end
$var wire 1 ! Y7 $end
$upscope $end
$upscope $end
$enddefinitions $end
#0
$dumpvars
0,
0+
0*
1)
1(
0'
0&
0%
0$
0#
0"
0!
$end
#10
0(
1'
1,
#20
1&
0'
0,
1+
#30
0&
1%
1,
#40
1$
0%
0,
0+
1*
#50
0$
1#
1,
#60
1"
0#
0,
1+
#70
0"
1!
1,
